gobbletgobblers/__init__.py
gobbletgobblers/__main__.py
gobbletgobblers.py-1.3.2.dist-info/METADATA
gobbletgobblers.py-1.3.2.dist-info/WHEEL
gobbletgobblers.py-1.3.2.dist-info/top_level.txt
gobbletgobblers.py-1.3.2.dist-info/RECORD
