Metadata-Version: 2.1
Name: gobbletgobblers.py
Version: 1.3.2
Summary: 有名ボドゲ、ゴブレットゴブラーズをPythonで使用可能にしたもの
Home-page: https://github.com/Req-kun/gobbletgobblers.py
Author: Aomi Vel / 碧海ベル
License: UNKNOWN
Keywords: gobbletgobblers gobblet gobblers
Platform: UNKNOWN
Classifier: Development Status :: 5 - Production/Stable
Classifier: License :: OSI Approved :: BSD License
Classifier: Programming Language :: Python
Classifier: Programming Language :: Python :: 3.9
Classifier: Topic :: Database
Classifier: Topic :: Software Development :: Libraries :: Python Modules
